epypackage/__init__.py
epypackage/arithmeticOperationBase.py
epypackage/arrayActionBase.py
epypackage/asyncPool.py
epypackage/asyncPoolGevent.py
epypackage/clipBoard.py
epypackage/clockUtil.py
epypackage/codeConv.py
epypackage/commonlyUtil.py
epypackage/configEnvUtil.py
epypackage/configUtil.py
epypackage/crypto.py
epypackage/dirkBase.py
epypackage/emailUtil.py
epypackage/emojiUtil.py
epypackage/eqrcode.py
epypackage/example.py
epypackage/excel_openpyxl.py
epypackage/excel_openpyxl2.py
epypackage/excel_xlwr.py
epypackage/ffmpeg.py
epypackage/imageUtil.py
epypackage/javscript.py
epypackage/mysqlUtil.py
epypackage/mysqlUtil2.py
epypackage/networkUtil.py
epypackage/practical.py
epypackage/processPoolUtil.py
epypackage/progiterUtil.py
epypackage/public.py
epypackage/redise.py
epypackage/regexpUtil.py
epypackage/stringBase.py
epypackage/stringUtil.py
epypackage/systemProcessingBase.py
epypackage/threadingUtil.py
epypackage/timeBase.py
epypackage/timeUtil.py
epypackage/typeConv.py
epypackage/win32apiUtil.py
epypackage-0.1.1.20220411.331.dist-info/LICENSE
epypackage-0.1.1.20220411.331.dist-info/METADATA
epypackage-0.1.1.20220411.331.dist-info/WHEEL
epypackage-0.1.1.20220411.331.dist-info/top_level.txt
epypackage-0.1.1.20220411.331.dist-info/RECORD
