Metadata-Version: 2.1
Name: epypackage
Version: 0.1.1.20220411.331
Summary: e->py
Home-page: https://github.com
Author: nuo
Author-email: nuo010@126.com
License: Apache 2
Keywords: e
Platform: UNKNOWN
License-File: LICENSE
